HiddenRequest/HiddenRequest.py
HiddenRequest/__init__.py
HiddenRequest/test/__init__.py
HiddenRequest/test/test_HiddenRequest.py
HiddenRequest-0.0.4.dist-info/LICENSE
HiddenRequest-0.0.4.dist-info/METADATA
HiddenRequest-0.0.4.dist-info/WHEEL
HiddenRequest-0.0.4.dist-info/top_level.txt
HiddenRequest-0.0.4.dist-info/RECORD
