Metadata-Version: 2.1
Name: HiddenRequest
Version: 0.0.4
Summary: A tool that builds on both requests and Torrequests to include a VPN and randomized headers
Author: Groseries
License: Copyright (c) 2018 The Python Packaging Authority        
Project-URL: Homepage, https://github.com/groseries/HiddenRequest
Project-URL: Bug Tracker, https://github.com/groseries/HiddenRequest/issues
Classifier: Programming Language :: Python :: 3
Classifier: License :: OSI Approved :: MIT License
Classifier: Operating System :: OS Independent
Requires-Python: >=3.7
License-File: LICENSE
Requires-Dist: requests
Requires-Dist: randomheaders
Requires-Dist: torrequest
